helloworld.py
helloworld_by_ariel-0.0.1.dist-info/METADATA
helloworld_by_ariel-0.0.1.dist-info/WHEEL
helloworld_by_ariel-0.0.1.dist-info/top_level.txt
helloworld_by_ariel-0.0.1.dist-info/RECORD
