Metadata-Version: 2.1
Name: helloworld-by-ariel
Version: 0.0.1
Summary: Say Hello
Home-page: UNKNOWN
License: UNKNOWN
Platform: UNKNOWN
Provides-Extra: dev
Requires-Dist: pytest (>=3.7) ; extra == 'dev'
